cmdop/__init__.py
cmdop/client.py
cmdop/config.py
cmdop/discovery.py
cmdop/exceptions.py
cmdop/logging.py
cmdop/py.typed
cmdop/_generated/__init__.py
cmdop/_generated/agent_messages_pb2.py
cmdop/_generated/agent_messages_pb2.pyi
cmdop/_generated/agent_messages_pb2_grpc.py
cmdop/_generated/common_types_pb2.py
cmdop/_generated/common_types_pb2.pyi
cmdop/_generated/common_types_pb2_grpc.py
cmdop/_generated/control_messages_pb2.py
cmdop/_generated/control_messages_pb2.pyi
cmdop/_generated/control_messages_pb2_grpc.py
cmdop/_generated/file_operations_pb2.py
cmdop/_generated/file_operations_pb2.pyi
cmdop/_generated/file_operations_pb2_grpc.py
cmdop/_generated/file_rpc_pb2.py
cmdop/_generated/file_rpc_pb2.pyi
cmdop/_generated/file_rpc_pb2_grpc.py
cmdop/_generated/message_pool.py
cmdop/_generated/py.typed
cmdop/_generated/rpc_messages_pb2.py
cmdop/_generated/rpc_messages_pb2.pyi
cmdop/_generated/rpc_messages_pb2_grpc.py
cmdop/_generated/service_pb2.py
cmdop/_generated/service_pb2.pyi
cmdop/_generated/service_pb2_grpc.py
cmdop/_generated/tunnel_pb2.py
cmdop/_generated/tunnel_pb2.pyi
cmdop/_generated/tunnel_pb2_grpc.py
cmdop/_generated/file_operations/__init__.py
cmdop/_generated/file_operations/archive_pb2.py
cmdop/_generated/file_operations/archive_pb2.pyi
cmdop/_generated/file_operations/archive_pb2_grpc.py
cmdop/_generated/file_operations/changes_pb2.py
cmdop/_generated/file_operations/changes_pb2.pyi
cmdop/_generated/file_operations/changes_pb2_grpc.py
cmdop/_generated/file_operations/common_pb2.py
cmdop/_generated/file_operations/common_pb2.pyi
cmdop/_generated/file_operations/common_pb2_grpc.py
cmdop/_generated/file_operations/directory_pb2.py
cmdop/_generated/file_operations/directory_pb2.pyi
cmdop/_generated/file_operations/directory_pb2_grpc.py
cmdop/_generated/file_operations/file_crud_pb2.py
cmdop/_generated/file_operations/file_crud_pb2.pyi
cmdop/_generated/file_operations/file_crud_pb2_grpc.py
cmdop/_generated/file_operations/hls_pb2.py
cmdop-0.1.28.dist-info/METADATA
cmdop-0.1.28.dist-info/WHEEL
cmdop-0.1.28.dist-info/licenses/LICENSE
cmdop-0.1.28.dist-info/RECORD
