Metadata-Version: 2.4
Name: cmdop
Version: 0.1.28
Summary: Python SDK for CMDOP agent interaction
Project-URL: Homepage, https://cmdop.com
Project-URL: Documentation, https://cmdop.com
Project-URL: Repository, https://github.com/markolofsen/cmdop-client
Author: CMDOP Team
License: MIT
License-File: LICENSE
Keywords: agent,automation,cmdop,terminal
Classifier: Development Status :: 3 - Alpha
Classifier: Intended Audience :: Developers
Classifier: License :: OSI Approved :: MIT License
Classifier: Programming Language :: Python :: 3
Classifier: Programming Language :: Python :: 3.10
Classifier: Programming Language :: Python :: 3.11
Classifier: Programming Language :: Python :: 3.12
Classifier: Topic :: Software Development :: Libraries :: Python Modules
Classifier: Typing :: Typed
Requires-Python: >=3.10
Requires-Dist: beautifulsoup4>=4.14.3
Requires-Dist: grpcio>=1.60.0
Requires-Dist: httpx>=0.27.0
Requires-Dist: protobuf>=4.25.0
Requires-Dist: pydantic-settings>=2.0.0
Requires-Dist: pydantic>=2.5.0
Requires-Dist: rich>=13.0.0
Requires-Dist: toon-python>=0.1.2
Provides-Extra: dev
Requires-Dist: grpcio-tools>=1.60.0; extra == 'dev'
Requires-Dist: mypy>=1.8.0; extra == 'dev'
Requires-Dist: pytest-asyncio>=0.23.0; extra == 'dev'
Requires-Dist: pytest-cov>=4.1.0; extra == 'dev'
Requires-Dist: pytest-grpc-aio>=0.3.0; extra == 'dev'
Requires-Dist: pytest>=8.0.0; extra == 'dev'
Requires-Dist: ruff>=0.1.0; extra == 'dev'
